arxiv_zotero/__init__.py
arxiv_zotero/__main__.py
arxiv_zotero/cli.py
arxiv_zotero/clients/__init__.py
arxiv_zotero/clients/arxiv_client.py
arxiv_zotero/clients/zotero_client.py
arxiv_zotero/config/__init__.py
arxiv_zotero/config/arxiv_config.py
arxiv_zotero/config/metadata_config.py
arxiv_zotero/core/__init__.py
arxiv_zotero/core/connector.py
arxiv_zotero/core/paper_processor.py
arxiv_zotero/core/search_params.py
arxiv_zotero/utils/credentials.py
arxiv_zotero/utils/pdf_manager.py
arxiv_zotero/utils/summarizer.py
arxiv_zotero_connector-0.1.0.dist-info/licenses/LICENSE
arxiv_zotero_connector-0.1.0.dist-info/METADATA
arxiv_zotero_connector-0.1.0.dist-info/WHEEL
arxiv_zotero_connector-0.1.0.dist-info/top_level.txt
arxiv_zotero_connector-0.1.0.dist-info/RECORD
