Metadata-Version: 2.4
Name: arxiv-zotero-connector
Version: 0.1.0
Summary: Automatically collect papers from ArXiv and organize them in your Zotero library with AI-powered summarization
Home-page: https://github.com/StepanKropachev/arxiv-zotero-connector
Author: Stepan Kropachev
Author-email: Stepan Kropachev <your.email@example.com>
License: MIT
Requires-Python: >=3.7
License-File: LICENSE
Dynamic: author
Dynamic: home-page
Dynamic: license-file
Dynamic: requires-python
